LICENSE
MANIFEST.in
README.rst
requirements.txt
setup.cfg
setup.py
WhydToGo.egg-info/PKG-INFO
WhydToGo.egg-info/SOURCES.txt
WhydToGo.egg-info/dependency_links.txt
WhydToGo.egg-info/entry_points.txt
WhydToGo.egg-info/requires.txt
WhydToGo.egg-info/top_level.txt
whydtogo/__init__.py
whydtogo/scraper.py