Metadata-Version: 1.1
Name: WhydToGo
Version: 0.4.0
Summary: Whyd To Go - Take your Whyd playlists away
Home-page: https://github.com/Djiit/whydtogo
Author: Julien Tanay
Author-email: julien.tanay@gmail.com
License: MIT
Keywords: whyd scraping youtube-dl
Platform: UNKNOWN
Classifier: Development Status :: 4 - Beta
Classifier: License :: OSI Approved :: MIT License
Classifier: Programming Language :: Python :: 2.7
Classifier: Programming Language :: Python :: 3
Classifier: Programming Language :: Python :: 3.3
Classifier: Programming Language :: Python :: 3.4
